logteehtml/__init__.py
logteehtml/__version__.py
logteehtml/core.py
logteehtml-0.1.0.dist-info/LICENSE
logteehtml-0.1.0.dist-info/METADATA
logteehtml-0.1.0.dist-info/WHEEL
logteehtml-0.1.0.dist-info/top_level.txt
logteehtml-0.1.0.dist-info/RECORD
