Metadata-Version: 2.1
Name: logteehtml
Version: 0.1.0
Summary: Comprehensive HTML logging with rich content support
Home-page: https://github.com/aaichert/logteehtml
Author: André Aichert
Author-email: André Aichert <aaichert@gmail.com>
Maintainer-email: André Aichert <aaichert@gmail.com>
License: MIT
Project-URL: Homepage, https://github.com/aaichert/logteehtml
Project-URL: Documentation, https://github.com/aaichert/logteehtml#readme
Project-URL: Repository, https://github.com/aaichert/logteehtml.git
Project-URL: Bug Tracker, https://github.com/aaichert/logteehtml/issues
Keywords: logging,html,rich,pillow,documentation
Classifier: Development Status :: 4 - Beta
Classifier: Intended Audience :: Developers
Classifier: License :: OSI Approved :: MIT License
Classifier: Operating System :: OS Independent
Classifier: Programming Language :: Python :: 3
Classifier: Programming Language :: Python :: 3.8
Classifier: Programming Language :: Python :: 3.9
Classifier: Programming Language :: Python :: 3.10
Classifier: Programming Language :: Python :: 3.11
Classifier: Programming Language :: Python :: 3.12
Classifier: Topic :: System :: Logging
Classifier: Topic :: Text Processing :: Markup :: HTML
Classifier: Topic :: Software Development :: Libraries :: Python Modules
Requires-Python: >=3.8
License-File: LICENSE
Requires-Dist: Pillow>=8.0.0
Provides-Extra: dev
Requires-Dist: pytest>=6.0.0; extra == "dev"
Requires-Dist: black; extra == "dev"
Requires-Dist: flake8; extra == "dev"
Requires-Dist: build; extra == "dev"
Requires-Dist: twine; extra == "dev"
Provides-Extra: rich
Requires-Dist: rich>=10.0.0; extra == "rich"
